crosszip/__init__.py
crosszip/crosszip.py
crosszip/exceptions.py
crosszip/plugin.py
crosszip/py.typed
crosszip-1.3.0.dist-info/METADATA
crosszip-1.3.0.dist-info/WHEEL
crosszip-1.3.0.dist-info/entry_points.txt
crosszip-1.3.0.dist-info/licenses/LICENSE.md
crosszip-1.3.0.dist-info/RECORD
