Metadata-Version: 2.4
Name: crosszip
Version: 1.3.0
Summary: Apply a given function to all combinations of elements from multiple iterables
Project-URL: Homepage, https://github.com/IndrajeetPatil/crosszip
Project-URL: Documentation, https://indrajeetpatil.github.io/crosszip/
Project-URL: Repository, https://github.com/IndrajeetPatil/crosszip
Project-URL: Issues, https://github.com/IndrajeetPatil/crosszip/issues
Project-URL: Changelog, https://github.com/IndrajeetPatil/crosszip/blob/main/CHANGELOG.md
Author-email: Indrajeet Patil <patilindrajeet.science@gmail.com>
License: # MIT License
License-File: LICENSE.md
Keywords: iterables
Classifier: Development Status :: 5 - Production/Stable
Classifier: Intended Audience :: Developers
Classifier: License :: OSI Approved :: MIT License
Classifier: Operating System :: OS Independent
Classifier: Programming Language :: Python
Classifier: Programming Language :: Python :: 3 :: Only
Classifier: Programming Language :: Python :: 3.10
Classifier: Programming Language :: Python :: 3.11
Classifier: Programming Language :: Python :: 3.12
Classifier: Programming Language :: Python :: 3.13
Classifier: Programming Language :: Python :: 3.14
Classifier: Topic :: Software Development :: Libraries :: Python Modules
Requires-Python: >=3.10
Requires-Dist: pytest>=8.4.2
